loading_bars/__init__.py
loading_bars/loading_bars.py
loading_bars-0.0.1.dist-info/LICENSE
loading_bars-0.0.1.dist-info/METADATA
loading_bars-0.0.1.dist-info/WHEEL
loading_bars-0.0.1.dist-info/top_level.txt
loading_bars-0.0.1.dist-info/RECORD
