Metadata-Version: 2.1
Name: loading-bars
Version: 0.0.1
Summary: Set of loading bars to make your life easy!
Home-page: https://github.com/AndoreKun/loading-bars.git
Author: André Pereira
Author-email: andrepereira180903@gmail.com
License: UNKNOWN
Platform: UNKNOWN
Classifier: Programming Language :: Python :: 3
Classifier: License :: OSI Approved :: MIT License
Classifier: Operating System :: OS Independent
